conduitlib/__init__.py
conduitlib/auth.py
conduitlib/plugin.py
conduitlib/util.py
unittests/__init__.py
unittests/test_auth.py
unittests/test_plugin.py
unittests/test_util.py
conduitlib-2.1.0.dist-info/METADATA
conduitlib-2.1.0.dist-info/WHEEL
conduitlib-2.1.0.dist-info/top_level.txt
conduitlib-2.1.0.dist-info/RECORD
